compas_assembly/__init__.py
compas_assembly/install.py
compas_assembly/algorithms/__init__.py
compas_assembly/algorithms/hull.py
compas_assembly/algorithms/hull_numpy.py
compas_assembly/algorithms/interfaces.py
compas_assembly/algorithms/interfaces_numpy.py
compas_assembly/algorithms/nnbrs.py
compas_assembly/data/__init__.py
compas_assembly/datastructures/__init__.py
compas_assembly/datastructures/assembly.py
compas_assembly/datastructures/block.py
compas_assembly/datastructures/interface.py
compas_assembly/geometry/__init__.py
compas_assembly/geometry/_geometry.py
compas_assembly/geometry/arch.py
compas_assembly/geometry/dome.py
compas_assembly/geometry/wall.py
compas_assembly/rhino/__init__.py
compas_assembly/rhino/install.py
compas_assembly/viewer/__init__.py
compas_assembly/viewer/app.py
compas_assembly-0.7.1.dist-info/LICENSE
compas_assembly-0.7.1.dist-info/METADATA
compas_assembly-0.7.1.dist-info/WHEEL
compas_assembly-0.7.1.dist-info/top_level.txt
compas_assembly-0.7.1.dist-info/RECORD
